ZeCo/__init__.py
ZeCo-0.20.dist-info/METADATA
ZeCo-0.20.dist-info/WHEEL
ZeCo-0.20.dist-info/top_level.txt
ZeCo-0.20.dist-info/RECORD
