Metadata-Version: 2.1
Name: ZeCo
Version: 0.20
Summary: this package is used to train an image classifier
Home-page: UNKNOWN
Author: UNKNOWN
Author-email: UNKNOWN
License: UNKNOWN
Platform: UNKNOWN
